gitea_actions_webscraper-0.0.5.dist-info/METADATA
gitea_actions_webscraper-0.0.5.dist-info/WHEEL
gitea_actions_webscraper/__init__.py
gitea_actions_webscraper/gitea_actions_webscraper.py
gitea_actions_webscraper-0.0.5.dist-info/RECORD
