Metadata-Version: 2.1
Name: gitea_actions_webscraper
Version: 0.0.5
Summary: Enable temporarily Gitea Actions web scraping.
Author: Benjamin Loison
Classifier: Programming Language :: Python :: 3
Classifier: Operating System :: OS Independent
Project-URL: Homepage, https://codeberg.org/Benjamin_Loison/Gitea_Actions_Webscraper
Project-URL: Bug tracker, https://codeberg.org/Benjamin_Loison/Gitea_Actions_Webscraper/issues
Requires-Python: >=3.7
Requires-Dist: requests
Requires-Dist: lxml
